Countrydetails/__init__.py
Countrydetails/cli.py
Countrydetails/countries.py
Countrydetails/country.py
Countrydetails/test.py
Countrydetails/cli_dir/__init__.py
Countrydetails/cli_dir/banner.py
Countrydetails/cli_dir/colors.py
Countrydetails/data/continents.json
Countrydetails/data/countries.json
Countrydetails/data/langtocountries.json
Countrydetails/data/region.json
Countrydetails/data/states.json
Countrydetails/data/countries/afghanistan.json
Countrydetails/data/countries/albania.json
Countrydetails/data/countries/algeria.json
Countrydetails/data/countries/american_samoa.json
Countrydetails/data/countries/angola.json
Countrydetails/data/countries/anguilla.json
Countrydetails/data/countries/antarctica.json
Countrydetails/data/countries/antigua_and_barbuda.json
Countrydetails/data/countries/argentina.json
Countrydetails/data/countries/armenia.json
Countrydetails/data/countries/aruba.json
Countrydetails/data/countries/ashmore_and_cartier_island.json
Countrydetails/data/countries/australia.json
Countrydetails/data/countries/austria.json
Countrydetails/data/countries/azerbaijan.json
Countrydetails/data/countries/bahamas.json
Countrydetails/data/countries/bahrain.json
Countrydetails/data/countries/bangladesh.json
Countrydetails/data/countries/barbados.json
Countrydetails/data/countries/belarus.json
Countrydetails/data/countries/belgium.json
Countrydetails/data/countries/belize.json
Countrydetails/data/countries/benin.json
Countrydetails/data/countries/bermuda.json
Countrydetails/data/countries/bhutan.json
Countrydetails/data/countries/bolivia.json
Countrydetails/data/countries/bosnia_and_herzegovina.json
Countrydetails/data/countries/botswana.json
Countrydetails/data/countries/brazil.json
Countrydetails/data/countries/british_virgin_islands.json
Countrydetails/data/countries/brunei.json
Countrydetails/data/countries/bulgaria.json
Countrydetails/data/countries/burkina_faso.json
Countrydetails/data/countries/burma.json
Countrydetails/data/countries/burundi.json
countrydata-1.0.6.dist-info/LICENSE
countrydata-1.0.6.dist-info/METADATA
countrydata-1.0.6.dist-info/WHEEL
countrydata-1.0.6.dist-info/entry_points.txt
countrydata-1.0.6.dist-info/top_level.txt
countrydata-1.0.6.dist-info/RECORD
