Metadata-Version: 2.1
Name: countrydata
Version: 1.0.6
Summary: An improved python package for retrieving data of all the countries in the world. Based on Manoj's
Home-page: 
Author: Gabi
Author-email: gfxsetup@gmail.com
License: MIT
Keywords: country,countrydata,countryinfo,country information,country data,country info
Classifier: License :: OSI Approved :: MIT License
Classifier: Programming Language :: Python :: 3
Classifier: Programming Language :: Python :: 3.7
License-File: LICENSE
